flayyer/__init__.py
flayyer/flayyer.py
flayyer-1.2.0.dist-info/WHEEL
flayyer-1.2.0.dist-info/METADATA
flayyer-1.2.0.dist-info/RECORD
