Metadata-Version: 2.1
Name: flayyer
Version: 1.2.0
Summary: FLAYYER.com helper classes and methods
Home-page: https://flayyer.com/
License: MIT
Author: Patricio López Juri
Author-email: patricio@flayyer.com
Requires-Python: >=3.6,<4.0
Classifier: License :: OSI Approved :: MIT License
Classifier: Programming Language :: Python :: 3
Classifier: Programming Language :: Python :: 3.6
Classifier: Programming Language :: Python :: 3.7
Classifier: Programming Language :: Python :: 3.8
Classifier: Programming Language :: Python :: 3.9
Requires-Dist: PyJWT (>=2.0.1,<3.0.0)
Requires-Dist: typing-extensions (>=3.7.4,<4.0.0)
Project-URL: Repository, https://github.com/flayyer/flayyer-python
